{"theme":"monokai","themeLight":"serika","themeDark":"serika_dark","autoSwitchTheme":false,"customTheme":true,"customThemeColors":["#272822","#ae81ff","#66d9ef","#e6db74","#1f201b","#e2e2dc","#f92672","#fd971f","#f92672","#fd971f"],"favThemes":["monokai"],"showKeyTips":true,"smoothCaret":"fast","codeUnindentOnBackspace":true,"quickRestart":"esc","punctuation":true,"numbers":true,"words":50,"time":30,"mode":"time","quoteLength":[1],"language":"english_5k","fontSize":2,"freedomMode":false,"difficulty":"normal","blindMode":false,"quickEnd":false,"caretStyle":"default","paceCaretStyle":"default","flipTestColors":false,"layout":"default","funbox":[],"confidenceMode":"off","indicateTypos":"replace","timerStyle":"mini","liveSpeedStyle":"mini","liveAccStyle":"mini","liveBurstStyle":"off","colorfulMode":false,"randomTheme":"off","timerColor":"main","timerOpacity":"1","stopOnError":"off","showAllLines":false,"keymapMode":"off","keymapStyle":"staggered","keymapLegendStyle":"lowercase","keymapLayout":"overrideSync","keymapShowTopRow":"layout","keymapSize":1,"fontFamily":"JetBrains_Mono","smoothLineScroll":false,"alwaysShowDecimalPlaces":true,"alwaysShowWordsHistory":false,"singleListCommandLine":"on","capsLockWarning":true,"playSoundOnError":"off","playSoundOnClick":"off","soundVolume":0.5,"startGraphsAtZero":true,"showOutOfFocusWarning":true,"paceCaret":"off","paceCaretCustomSpeed":100,"repeatedPace":true,"accountChart":["on","on","on","on"],"minWpm":"off","minWpmCustomSpeed":50,"highlightMode":"letter","typingSpeedUnit":"wpm","ads":"result","hideExtraLetters":false,"strictSpace":false,"minAcc":"custom","minAccCustom":80,"monkey":false,"repeatQuotes":"off","oppositeShiftMode":"off","customBackground":"","customBackgroundSize":"cover","customBackgroundFilter":[0,1,1,1],"customLayoutfluid":["qwerty"],"customPolyglot":["english_5k","russian_50k","git","code_python_1k","code_java","code_kotlin"],"monkeyPowerLevel":"off","minBurst":"off","minBurstCustomSpeed":100,"burstHeatmap":false,"britishEnglish":false,"lazyMode":false,"showAverage":"both","tapeMode":"off","tapeMargin":50,"maxLineWidth":0}
